cronian/__init__.py
cronian/all_assets.py
cronian/base_model.py
cronian/configuration.py
cronian/demands.py
cronian/electric_power.py
cronian/explicit_heat.py
cronian/feasible_consumption.py
cronian/generators.py
cronian/local_balance.py
cronian/objective_func.py
cronian/prosumers.py
cronian/results.py
cronian/run_co_optimization.py
cronian/store_factory.py
cronian/system_balance.py
cronian/validate.py
cronian/DERs/__init__.py
cronian/DERs/converter.py
cronian/DERs/storage.py
cronian/DERs/vre_generator.py
cronian-0.3.2.dist-info/licenses/LICENSE
cronian-0.3.2.dist-info/licenses/NOTICE
cronian-0.3.2.dist-info/METADATA
cronian-0.3.2.dist-info/WHEEL
cronian-0.3.2.dist-info/top_level.txt
cronian-0.3.2.dist-info/RECORD
