Metadata-Version: 2.4
Name: cronian
Version: 0.3.2
Summary: Build energy models with flexible demand from simple configuration files.
Author-email: Christian Doh Dinga <c.dohdinga@tudelft.nl>, Sander van Rijn <s.vanrijn@esciencecenter.nl>
License: MIT License
Project-URL: Repository, https://gitlab.tudelft.nl/demoses/cronian
Project-URL: Issues, https://gitlab.tudelft.nl/demoses/cronian/-/issues
Project-URL: Changelog, https://gitlab.tudelft.nl/demoses/cronian/-/blob/main/CHANGELOG.md
Keywords: energy transition,flexibility
Requires-Python: >=3.10
License-File: LICENSE
License-File: NOTICE
Requires-Dist: Pyomo
Requires-Dist: pandas
Provides-Extra: dev
Requires-Dist: build; extra == "dev"
Requires-Dist: bump-my-version; extra == "dev"
Requires-Dist: coverage[toml]; extra == "dev"
Requires-Dist: myst_parser; extra == "dev"
Requires-Dist: pyprojroot; extra == "dev"
Requires-Dist: pytest; extra == "dev"
Requires-Dist: pytest-cov; extra == "dev"
Requires-Dist: ruff; extra == "dev"
Requires-Dist: sphinx; extra == "dev"
Requires-Dist: sphinx_rtd_theme; extra == "dev"
Requires-Dist: sphinx-autoapi; extra == "dev"
Requires-Dist: tox; extra == "dev"
Provides-Extra: docs
Requires-Dist: sphinx; extra == "docs"
Requires-Dist: sphinx_copybutton; extra == "docs"
Requires-Dist: sphinx_rtd_theme; extra == "docs"
Requires-Dist: sphinx-autoapi; extra == "docs"
Provides-Extra: gurobi
Requires-Dist: gurobipy; extra == "gurobi"
Provides-Extra: publishing
Requires-Dist: build; extra == "publishing"
Requires-Dist: twine; extra == "publishing"
Requires-Dist: wheel; extra == "publishing"
Dynamic: license-file
